trainingsong/__init__.py
trainingsong/core.py
trainingsong/db_utils.py
trainingsong/server/.gitignore
trainingsong/server/__init__.py
trainingsong/server/api.py
trainingsong/server/billboard_io.py
trainingsong/server/db.py
trainingsong/server/hard_coded.py
trainingsong/server/spotify.py
trainingsong/ts_utils.py
training_song-0.2.2.dist-info/METADATA
training_song-0.2.2.dist-info/WHEEL
training_song-0.2.2.dist-info/RECORD
