Metadata-Version: 2.1
Name: training-song
Version: 0.2.2
Summary: Audio Motivation for Data Scientists and ML Engineers
License: MIT
Author: koayon
Author-email: koayon@gmail.com
Requires-Python: >=3.8,<4.0
Classifier: License :: OSI Approved :: MIT License
Classifier: Programming Language :: Python :: 3
Classifier: Programming Language :: Python :: 3.8
Classifier: Programming Language :: Python :: 3.9
Classifier: Programming Language :: Python :: 3.10
Classifier: Programming Language :: Python :: 3.11
Requires-Dist: asyncpg (>=0.27.0,<0.28.0)
Requires-Dist: billboard-py (>=7.0.0,<8.0.0)
Requires-Dist: cryptography (>=38.0.0,<39.0.0)
Requires-Dist: databases (>=0.5.2,<0.6.0)
Requires-Dist: fastapi (>=0.95.1,<0.96.0)
Requires-Dist: httpcore (>=0.15,<0.16)
Requires-Dist: httpx (>=0.23.0,<0.24.0)
Requires-Dist: lyricsgenius (>=3.0.1,<4.0.0)
Requires-Dist: psycopg2-binary (>=2.9.3,<3.0.0)
Requires-Dist: pytest-asyncio (>=0.15.1,<0.16.0)
Requires-Dist: python-dotenv (>=0.19.1,<0.20.0)
Requires-Dist: responses (>=0.13.4,<0.14.0)
Requires-Dist: spotipy (>=2.23.0,<3.0.0)
Requires-Dist: sqlalchemy (>=1.4.26,<2.0.0)
Requires-Dist: starlette (>=0.27.0,<0.28.0)
Requires-Dist: uvicorn (>=0.22.0,<0.23.0)
